telegram_dsl/__init__.py
telegram_dsl/app.py
telegram_dsl/diagnostics/map_view.py
telegram_dsl/flow/schema.py
telegram_dsl/flow/states.py
telegram_dsl/framework/actions.py
telegram_dsl/framework/buttons.py
telegram_dsl/framework/decorators.py
telegram_dsl/framework/docs.py
telegram_dsl/framework/errors.py
telegram_dsl/framework/handlers.py
telegram_dsl/framework/outputs.py
telegram_dsl/framework/payloads.py
telegram_dsl/framework/rendering.py
telegram_dsl/framework/responses.py
telegram_dsl/internal/bootstrap.py
telegram_dsl/internal/constants.py
telegram_dsl/internal/errors.py
telegram_dsl/internal/inspect.py
telegram_dsl/internal/lifecycle.py
telegram_dsl/internal/telegram_methods.py
telegram_dsl/internal/engine/middleware.py
telegram_dsl/internal/engine/rendering.py
telegram_dsl/internal/engine/responders.py
telegram_dsl/internal/handlers/fallback.py
telegram_dsl/internal/handlers/map.py
telegram_dsl/internal/handlers/metadata.py
telegram_dsl/internal/handlers/states.py
telegram_dsl/internal/handlers/validation.py
telegram_dsl/internal/middleware/hooks.py
telegram_dsl/internal/responses/matchers.py
telegram_dsl/internal/responses/send.py
telegram_dsl-0.1.0.dist-info/licenses/LICENSE
telegram_dsl-0.1.0.dist-info/METADATA
telegram_dsl-0.1.0.dist-info/WHEEL
telegram_dsl-0.1.0.dist-info/top_level.txt
telegram_dsl-0.1.0.dist-info/RECORD
