Metadata-Version: 2.4
Name: telegram-dsl
Version: 0.1.0
Summary: A lightweight DSL on top of python-telegram-bot for writing Telegram bots with decorators and explicit outputs.
Author-email: Cesare Iurlaro <ciurlaro@users.noreply.github.com>
License: MIT License
Project-URL: Homepage, https://github.com/ciurlaro/telegram-dsl
Project-URL: Repository, https://github.com/ciurlaro/telegram-dsl
Project-URL: Issues, https://github.com/ciurlaro/telegram-dsl/issues
Keywords: telegram,bot,python-telegram-bot,dsl
Classifier: Development Status :: 3 - Alpha
Classifier: Intended Audience :: Developers
Classifier: License :: OSI Approved :: MIT License
Classifier: Programming Language :: Python :: 3
Classifier: Programming Language :: Python :: 3 :: Only
Classifier: Programming Language :: Python :: 3.11
Classifier: Programming Language :: Python :: 3.12
Classifier: Programming Language :: Python :: 3.13
Classifier: Topic :: Software Development :: Libraries
Requires-Python: >=3.11
License-File: LICENSE
Requires-Dist: python-telegram-bot==22.0
Requires-Dist: decorator==5.1.1
Requires-Dist: APScheduler==3.11.0
Provides-Extra: dev
Requires-Dist: pytest==8.2.2; extra == "dev"
Requires-Dist: pytest-asyncio==0.23.7; extra == "dev"
Requires-Dist: build==1.2.2.post1; extra == "dev"
Requires-Dist: twine==6.0.1; extra == "dev"
Dynamic: license-file
